checkexpect/__init__.py
checkexpect/core.py
checkexpect-1.0.19.dist-info/DESCRIPTION.rst
checkexpect-1.0.19.dist-info/METADATA
checkexpect-1.0.19.dist-info/RECORD
checkexpect-1.0.19.dist-info/WHEEL
checkexpect-1.0.19.dist-info/metadata.json
checkexpect-1.0.19.dist-info/top_level.txt
