Metadata-Version: 2.0
Name: checkexpect
Version: 1.0.19
Summary: checkexpect is a simple unit testing framework for python development
Home-page: https://github.com/dareljohnson/checkexpect-py
Author: Darel Johnson
Author-email: dareljohnson@yahoo.com
License: MIT
Download-URL: https://github.com/dareljohnson/checkexpect-py/tarball/0.1
Requires-Dist: colorama
